pytimebudget/__init__.py
pytimebudget/analyzer.py
pytimebudget/config.py
pytimebudget/core.py
pytimebudget/project.py
pytimebudget/storage.py
pytimebudget/utils.py
pytimebudget/warnings.py
pytimebudget-0.1.1.dist-info/METADATA
pytimebudget-0.1.1.dist-info/WHEEL
pytimebudget-0.1.1.dist-info/top_level.txt
pytimebudget-0.1.1.dist-info/RECORD
