Metadata-Version: 2.4
Name: pytimebudget
Version: 0.1.1
Summary: Zero-effort performance regression detection for Python
Author-email: veliqq <veliqorg@proton.me>
License: MIT
Project-URL: Homepage, https://github.com/veliqq/pytimebudget
Project-URL: Repository, https://github.com/veliqq/pytimebudget
Requires-Python: >=3.8
